README.txt
setup.py
Products/__init__.py
Products.MenuNavigation.egg-info/PKG-INFO
Products.MenuNavigation.egg-info/SOURCES.txt
Products.MenuNavigation.egg-info/dependency_links.txt
Products.MenuNavigation.egg-info/entry_points.txt
Products.MenuNavigation.egg-info/namespace_packages.txt
Products.MenuNavigation.egg-info/not-zip-safe
Products.MenuNavigation.egg-info/requires.txt
Products.MenuNavigation.egg-info/top_level.txt
Products/MenuNavigation/MenuNavigation.py
Products/MenuNavigation/__init__.py
Products/MenuNavigation/changes.txt
Products/MenuNavigation/config.py
Products/MenuNavigation/configure.zcml
Products/MenuNavigation/readme.txt
Products/MenuNavigation/tests.py
Products/MenuNavigation/version.txt
Products/MenuNavigation/zope.interface.interface-plone.global_sections
Products/MenuNavigation/zope2.py
Products/MenuNavigation/Extensions/Install.py.bak
Products/MenuNavigation/profiles/default/metadata.xml
Products/MenuNavigation/profiles/default/skins.xml
Products/MenuNavigation/profiles/default/types.xml
Products/MenuNavigation/profiles/default/types/MenuPage.xml
Products/MenuNavigation/skins/MenuNavigation/info_portlet.pt
Products/MenuNavigation/skins/MenuNavigation/info_portlet_get.py
Products/MenuNavigation/skins/MenuNavigation/menu_description.pt
docs/HISTORY.txt
docs/INSTALL.txt
docs/LICENSE.GPL
docs/LICENSE.txt