Metadata-Version: 1.1
Name: Products.MenuNavigation
Version: 1.0b2
Summary: A simple addition to the navigation menus for extra information
Home-page: http://www.nidelven-it.no/d
Author: Nidelven IT LTD
Author-email: info@nidelven-it.no
License: GPL
Keywords: plone navigation information
Platform: UNKNOWN
Classifier: Framework :: Plone
Classifier: Programming Language :: Python
